setup.py
pyrcareworld/__init__.py
pyrcareworld/base_env.py
pyrcareworld/communicator.py
pyrcareworld/env_utils.py
pyrcareworld/environment.py
pyrcareworld/exception.py
pyrcareworld/logging_util.py
pyrcareworld/mock_communicator.py
pyrcareworld/rpc_communicator.py
pyrcareworld/rpc_utils.py
pyrcareworld/timers.py
pyrcareworld.egg-info/PKG-INFO
pyrcareworld.egg-info/SOURCES.txt
pyrcareworld.egg-info/dependency_links.txt
pyrcareworld.egg-info/not-zip-safe
pyrcareworld.egg-info/requires.txt
pyrcareworld.egg-info/top_level.txt
pyrcareworld/agents/__init__.py
pyrcareworld/agents/human.py
pyrcareworld/agents/robot.py
pyrcareworld/attributes/__init__.py
pyrcareworld/attributes/activelightsensor_attr.py
pyrcareworld/attributes/base_attr.py
pyrcareworld/attributes/camera_attr.py
pyrcareworld/attributes/cloth_attr.py
pyrcareworld/attributes/collider_attr.py
pyrcareworld/attributes/controller_attr.py
pyrcareworld/attributes/custom_attr.py
pyrcareworld/attributes/digit_attr.py
pyrcareworld/attributes/gameobject_attr.py
pyrcareworld/attributes/graspsim_attr.py
pyrcareworld/attributes/humanarticulation_attr.py
pyrcareworld/attributes/humanbody_attr.py
pyrcareworld/attributes/pointcloud_attr.py
pyrcareworld/attributes/rcarecontroller_attr.py
pyrcareworld/attributes/rigidbody_attr.py
pyrcareworld/attributes/tactilesensor_attr.py
pyrcareworld/communicator_objects/__init__.py
pyrcareworld/communicator_objects/agent_action_pb2.py
pyrcareworld/communicator_objects/agent_info_action_pair_pb2.py
pyrcareworld/communicator_objects/agent_info_pb2.py
pyrcareworld/communicator_objects/brain_parameters_pb2.py
pyrcareworld/communicator_objects/capabilities_pb2.py
pyrcareworld/communicator_objects/command_pb2.py
pyrcareworld/communicator_objects/custom_reset_parameters_pb2.py
pyrcareworld/communicator_objects/demonstration_meta_pb2.py
pyrcareworld/communicator_objects/engine_configuration_pb2.py
pyrcareworld/communicator_objects/header_pb2.py
pyrcareworld/communicator_objects/observation_pb2.py
pyrcareworld/communicator_objects/space_type_pb2.py
pyrcareworld/communicator_objects/training_analytics_pb2.py
pyrcareworld/communicator_objects/unity_input_pb2.py
