Metadata-Version: 2.1
Name: pyrcareworld
Version: 1.0.0
Summary: RCareWorld python interface
Home-page: https://github.com/empriselab/RCareWorld
Author: Ruolin Ye
Author-email: ry273@cornell.edu
License: UNKNOWN
Platform: UNKNOWN
Requires-Python: >=3.6.1
